Metadata-Version: 2.1
Name: dni
Version: 0.2.0
Summary: Deal with Spanish DNIs in a Pythonic way.
Home-page: https://github.com/pmartincalvo/dni
Author: Pablo Martin Calvo
Author-email: pablomartincalvo+dni@gmail.com
License: MIT License
Project-URL: Documentation, https://dni.readthedocs.io
Project-URL: Source, https://github.com/pmartincalvo/dni
Platform: UNKNOWN
Requires-Python: >=3.5
